Workbook
Name Query1: #REF!
Name Query1: #REF!

Sheet Cumulative data
A1: Summary Sheet of First Six Month Transactions
C2: Particulars | D2: Mid Jul 2011-Mid Jan 2012 | F2: Mid Jul 2012-Mid Jan 2013 | H2: Change | I2: Mid Jul 2013-Mid Jan 2014 | K2: Change
D3: 2068/69 | F3: 2069/70 | I3: 2070/71
D4: Share units | E4: Amount | F4: Share units | G4: Amount | H4: in | I4: Share units | J4: Amount | K4: in
D5: ( '000 ) | E5: Rs. in million | F5: ( '000 ) | G5: Rs. in million | H5: % | I5: ( '000 ) | J5: Rs. in million | K5: %
B6: 1 | C6: Turnover | D6: =SUM(D7:D20) -> 20584.08 | E6: =SUM(E7:E20) -> 4406.46 | F6: =SUM(F7:F20) -> 33849.96 | G6: =SUM(G7:G20) -> 9996.25 | H6: =SUM(G6-E6)*100/E6 -> 126.85444 | I6: =SUM(I7:I21) -> 85099.405 | J6: =SUM(J7:J19) -> 28333.207 | K6: =SUM(J6-G6)*100/G6 -> 183.43836
B7: A | C7: Commercial Bank | D7: 4989.31 | E7: 1600.83 | F7: 18993.3 | G7: 6312.67 | H7: =SUM(G7-E7)*100/E7 -> 294.33731 | I7: 40411.71 | J7: 16699.17 | K7: =SUM(J7-G7)*100/G7 -> 164.53418
B8: B | C8: Finance | D8: 1210.26 | E8: 154.33 | F8: 1544.23 | G8: 201.96 | H8: =SUM(G8-E8)*100/E8 -> 30.862438 | I8: 2119.22 | J8: 404.92 | K8: =SUM(J8-G8)*100/G8 -> 100.49515
B9: C | C9: Hotel | D9: 1295.59 | E9: 170.02 | F9: 155.24 | G9: 34.88 | H9: =SUM(G9-E9)*100/E9 -> -79.484766 | I9: 681.15 | J9: 200.28 | K9: =SUM(J9-G9)*100/G9 -> 474.19725
B10: D | C10: Manufacturing & Processing | D10: 1021.08 | E10: 788.46 | F10: 1.98 | G10: 10.68 | H10: =SUM(G10-E10)*100/E10 -> -98.645461 | I10: 621.3 | J10: 88.11 | K10: =SUM(J10-G10)*100/G10 -> 725
B11: E | C11: Other | D11: 137.71 | E11: 57.48 | F11: 632.65 | G11: 389.6 | H11: =SUM(G11-E11)*100/E11 -> 577.80097 | I11: 665.79 | J11: 412.36 | K11: =SUM(J11-G11)*100/G11 -> 5.8418891
B12: F | C12: Hydro Power | D12: 5156.77 | E12: 703.83 | F12: 1773.79 | G12: 1304.36 | H12: =SUM(G12-E12)*100/E12 -> 85.32316 | I12: 4308.97 | J12: 2197.84 | K12: =SUM(J12-G12)*100/G12 -> 68.499494
B13: G | C13: Trading | D13: 1.29 | E13: 3.46 | F13: 1.4 | G13: 2.44 | H13: =SUM(G13-E13)*100/E13 -> -29.479769 | I13: 2.04 | J13: 3.55 | K13: =SUM(J13-G13)*100/G13 -> 45.491803
B14: H | C14: Insurance | D14: 722.59 | E14: 136.27 | F14: 2091.45 | G14: 659.21 | H14: =SUM(G14-E14)*100/E14 -> 383.75284 | I14: 5220.55 | J14: 3184.97 | K14: =SUM(J14-G14)*100/G14 -> 383.14953
B15: I | C15: Development Bank | D15: 2870.17 | E15: 352.37 | F15: 3907.11 | G15: 535.86 | H15: =SUM(G15-E15)*100/E15 -> 52.073105 | I15: 8419.42 | J15: 2034.92 | K15: =SUM(J15-G15)*100/G15 -> 279.74844
B16: J | C16: Mutual Fund | D16: 50.6 | E16: 1.68 | F16: 417.75 | G16: 10.68 | H16: =SUM(G16-E16)*100/E16 -> 535.71429 | I16: 11193.39 | J16: 123.95 | K16: =SUM(J16-G16)*100/G16 -> 1060.5805
B17: K | C17: Preffered Stock | D17: 0.33 | E17: 0.31 | F17: 12.84 | G17: 9.72 | H17: =SUM(G17-E17)*100/E17 -> 3035.4839 | I17: 18.51 | J17: 15.86 | K17: =SUM(J17-G17)*100/G17 -> 63.168724
B18: L | C18: Promotor Share | D18: 3128.38 | E18: 437.42 | F18: 4318.22 | G18: 524.19 | H18: =SUM(G18-E18)*100/E18 -> 19.83677 | I18: 6576.71 | J18: 1606.03 | K18: =SUM(J18-G18)*100/G18 -> 206.38318
C19: Odd-Lot + Mannual Trade | I19: 4860.645 | J19: 1361.2468
C20: Corporate Bond
C21: Government Bond | D21: 1000 | E21: 103
B22: 2 | C22: Market Days | D22: 117 | F22: 115 | I22: 135 | K22: =SUM(I22-F22)*100/F22 -> 17.391304
B23: 3 | C23: Average Daily Turnover | D23: 113.50376 | E23: 29.585726 | F23: =+F7/F22 -> 165.15913 | G23: =+G7/F22 -> 54.892783 | I23: =+I6/I22 -> 630.36596 | J23: =+J6/I22 -> 209.87561 | K23: =SUM(J23-G23)*100/G23 -> 282.33734
B24: 4 | C24: Number of Transactions | D24: 136855 | F24: 155021 | H24: =SUM(F24-D24)*100/D24 -> 13.273903 | I24: 263192 | K24: =SUM(I24-F24)*100/F24 -> 69.778288
B25: 5 | C25: Number of Scrips Traded | D25: 195 | F25: 203 | H25: =SUM(F25-D25)*100/D25 -> 4.1025641 | I25: 230 | K25: =SUM(I25-F25)*100/F25 -> 13.300493
B26: 7 | C26: Number of Companies Listed | D26: 195 | F26: 214 | I26: 234 | K26: =SUM(I26-F26)*100/F26 -> 9.3457944
B27: 8 | C27: Total Paid Up Value of Listed Shares | E27: 93817 | G27: 106449 | H27: =SUM(G27-E27)*100/E27 -> 13.464511 | J27: 136817 | K27: =SUM(J27-G27)*100/G27 -> 28.528215
B28: 9 | C28: Total Number of Listed Securities | D28: 931729 | F28: 1098471 | H28: =SUM(F28-D28)*100/D28 -> 17.895976 | I28: 1418105 | K28: =SUM(I28-F28)*100/F28 -> 29.098083
B29: 10 | C29: Market Capitalization | E29: 349283.36 | G29: 300428.79 | H29: =SUM(G29-E29)*100/E29 -> -13.987088 | J29: 799760.34 | K29: =SUM(J29-G29)*100/G29 -> 166.20629
C30: NEPSE Index
B31: - | C31: High | E31: 472.29 | G31: 380.23 | H31: =SUM(G31-E31)*100/E31 -> -19.492261 | J31: 806.66 | K31: =SUM(J31-G31)*100/G31 -> 112.15054
B32: - | C32: Low | E32: 390.97 | G32: 312.5 | H32: =SUM(G32-E32)*100/E32 -> -20.070594 | J32: 509.36 | K32: =SUM(J32-G32)*100/G32 -> 62.9952
B33: - | C33: Closing | E33: 402.75 | G33: 323.62 | H33: =SUM(G33-E33)*100/E33 -> -19.647424 | J33: 787.05 | K33: =SUM(J33-G33)*100/G33 -> 143.2019
B34: 11 | C34: Market Capitalization of Group -A | E34: 276017.5 | G34: 260732.4 | H34: =SUM(G34-E34)*100/E34 -> -5.5377286 | J34: 647127.66 | K34: =SUM(J34-G34)*100/G34 -> 148.1961
B35: 12 | C35: Total Paid Up Value of Group - A | E35: 45370 | G35: 82240 | H35: =SUM(G35-E35)*100/E35 -> 81.265153 | J35: 97071 | K35: =SUM(J35-G35)*100/G35 -> 18.033804
B36: 13 | C36: NEPSE Sensitive Index
B37: - | C37: High | E37: 114.83 | G37: 94.26 | H37: =SUM(G37-E37)*100/E37 -> -17.913437 | J37: 201.62 | K37: =SUM(J37-G37)*100/G37 -> 113.89773
B38: - | C38: Low | E38: 95.79 | G38: 77.4 | H38: =SUM(G38-E38)*100/E38 -> -19.198246 | J38: 128.3 | K38: =SUM(J38-G38)*100/G38 -> 65.762274
B39: - | C39: Closing | E39: 99.39 | G39: 80.29 | H39: =SUM(G39-E39)*100/E39 -> -19.217225 | J39: 193.38 | K39: =SUM(J39-G39)*100/G39 -> 140.85191
B40: 14 | C40: NEPSE Float Index
B41: - | C41: High | E41: 43.56 | G41: 32.15 | H41: =SUM(G41-E41)*100/E41 -> -26.193756 | J41: 47.28 | K41: =SUM(J41-G41)*100/G41 -> 47.060653
B42: - | C42: Low | E42: 33.51 | G42: 25.05 | H42: =SUM(G42-E42)*100/E42 -> -25.246195 | J42: 30.93 | K42: =SUM(J42-G42)*100/G42 -> 23.473054
B43: - | C43: Closing | E43: 34.39 | G43: 25.69 | H43: =SUM(G43-E43)*100/E43 -> -25.298052 | J43: 45.74 | K43: =SUM(J43-G43)*100/G43 -> 78.045932

Sheet Back year's Summary
A1: Comparative Summary Sheet of Transactions with Previous Years
C2: Particulars | D2: Dec-Jan 2012 (Poush 2068) | F2: Dec-Jan 2013 (Poush 2069) | H2: Change | I2: Dec-Jan 2014 (Poush 2070) | K2: Change
D3: Share units | E3: Amount | F3: Share units | G3: Amount | H3: in | I3: Share units | J3: Amount | K3: in
D4: ( '000 ) | E4: Rs. in million | F4: ( '000 ) | G4: Rs. in million | H4: % | I4: ( '000 ) | J4: Rs. in million | K4: %
B5: 1 | C5: Turnover | D5: 3509.8 | E5: 664.87 | F5: ='[1]Summary Sheet'!F8 -> 5484.46 | G5: ='[1]Summary Sheet'!G8 -> 1884.89 | H5: =SUM(G5-E5)*100/E5 -> 183.49753 | I5: ='Summary Sheet'!I8 -> 18093.87 | J5: ='Summary Sheet'!J8 -> 8050.22 | K5: =SUM(J5-G5)*100/G5 -> 327.0923
B6: A | C6: Commercial Bank | D6: 808.16 | E6: 258.86 | F6: ='[1]Summary Sheet'!F9 -> 3952.58 | G6: ='[1]Summary Sheet'!G9 -> 1412.55 | H6: =SUM(G6-E6)*100/E6 -> 445.68106 | I6: ='Summary Sheet'!I9 -> 10445.33 | J6: ='Summary Sheet'!J9 -> 5393.14 | K6: =SUM(J6-G6)*100/G6 -> 281.80171
B7: B | C7: Finance | D7: 217.32 | E7: 24.83 | F7: ='[1]Summary Sheet'!F10 -> 294.31 | G7: ='[1]Summary Sheet'!G10 -> 42.72 | H7: =SUM(G7-E7)*100/E7 -> 72.04994 | I7: ='Summary Sheet'!I10 -> 550.01 | J7: ='Summary Sheet'!J10 -> 131.44 | K7: =SUM(J7-G7)*100/G7 -> 207.6779
B8: C | C8: Hotel | D8: 2.75 | E8: 0.22 | F8: ='[1]Summary Sheet'!F11 -> 33.85 | G8: ='[1]Summary Sheet'!G11 -> 9.22 | H8: =SUM(G8-E8)*100/E8 -> 4090.9091 | I8: ='Summary Sheet'!I11 -> 100.26 | J8: ='Summary Sheet'!J11 -> 31.29 | K8: =SUM(J8-G8)*100/G8 -> 239.37093
B9: D | C9: Manufacturing & Processing | D9: 0.24 | E9: 1.13 | F9: ='[1]Summary Sheet'!F12 -> 0.33 | G9: ='[1]Summary Sheet'!G12 -> 0.75 | H9: =SUM(G9-E9)*100/E9 -> -33.628319 | I9: ='Summary Sheet'!I12 -> 2.24 | J9: ='Summary Sheet'!J12 -> 4.19 | K9: 0
B10: E | C10: Other | D10: 20.25 | E10: 8.7 | F10: ='[1]Summary Sheet'!F13 -> 90.9 | G10: ='[1]Summary Sheet'!G13 -> 60.07 | H10: =SUM(G10-E10)*100/E10 -> 590.45977 | I10: ='Summary Sheet'!I13 -> 244.39 | J10: ='Summary Sheet'!J13 -> 164 | K10: =SUM(J10-G10)*100/G10 -> 173.01482
B11: F | C11: Hydro Power | D11: 1342.35 | E11: 200.8 | F11: ='[1]Summary Sheet'!F14 -> 199.67 | G11: ='[1]Summary Sheet'!G14 -> 173.8 | H11: =SUM(G11-E11)*100/E11 -> -13.446215 | I11: ='Summary Sheet'!I14 -> 760.25 | J11: ='Summary Sheet'!J14 -> 547.05 | K11: =SUM(J11-G11)*100/G11 -> 214.75834
B12: G | C12: Trading | D12: 0.57 | E12: 1.5 | F12: ='[1]Summary Sheet'!F15 -> 0 | G12: ='[1]Summary Sheet'!G15 -> 0 | H12: =SUM(G12-E12)*100/E12 -> -100 | I12: ='Summary Sheet'!I15 -> 1.03 | J12: ='Summary Sheet'!J15 -> 1.8 | K12: 0
B13: H | C13: Insurance | D13: 105.84 | E13: 18.91 | F13: ='[1]Summary Sheet'!F16 -> 185.4 | G13: ='[1]Summary Sheet'!G16 -> 78.73 | H13: =SUM(G13-E13)*100/E13 -> 316.34056 | I13: ='Summary Sheet'!I16 -> 852.77 | J13: ='Summary Sheet'!J16 -> 830.77 | K13: =SUM(J13-G13)*100/G13 -> 955.21402
B14: I | C14: Development Bank | D14: 408.17 | E14: 48.99 | F14: ='[1]Summary Sheet'!F17 -> 549.07 | G14: ='[1]Summary Sheet'!G17 -> 74.88 | H14: =SUM(G14-E14)*100/E14 -> 52.84752 | I14: ='Summary Sheet'!I17 -> 2240.58 | J14: ='Summary Sheet'!J17 -> 573.12 | K14: =SUM(J14-G14)*100/G14 -> 665.38462
B15: J | C15: Mutual Fund | D15: 0 | E15: 0 | F15: ='[1]Summary Sheet'!F18 -> 1.1 | G15: ='[1]Summary Sheet'!G18 -> 0.03 | H15: 0 | I15: ='Summary Sheet'!I18 -> 2403.38 | J15: ='Summary Sheet'!J18 -> 30.5 | K15: =SUM(J15-G15)*100/G15 -> 101566.67
B16: K | C16: Preferred Stock | D16: 0.05 | E16: 0.04 | F16: ='[1]Summary Sheet'!F19 -> 0.54 | G16: ='[1]Summary Sheet'!G19 -> 0.38 | H16: 0 | I16: ='Summary Sheet'!I19 -> 0.01 | J16: ='Summary Sheet'!J19 -> 0.01 | K16: =SUM(J16-G16)*100/G16 -> -97.368421
C17: Promotor Share | D17: 604.1 | E17: 100.89 | F17: ='[1]Summary Sheet'!F20 -> 176.71 | G17: ='[1]Summary Sheet'!G20 -> 31.76 | H17: =SUM(G17-E17)*100/E17 -> -68.52017 | I17: ='Summary Sheet'!I20 -> 493.64 | J17: ='Summary Sheet'!J20 -> 342.92 | K17: =SUM(J17-G17)*100/G17 -> 979.72292
C18: Corporate Bond
C19: Government Bond
B20: 2 | C20: Market days | D20: 19 | F20: ='[1]Summary Sheet'!F23 -> 19 | I20: ='Summary Sheet'!I23 -> 19
B21: 3 | C21: Average daily turnover | D21: 184.72632 | E21: 34.993158 | F21: ='[1]Summary Sheet'!F24 -> 288.65579 | G21: ='[1]Summary Sheet'!G24 -> 99.204737 | I21: ='Summary Sheet'!I24 -> 952.30895 | J21: ='Summary Sheet'!J24 -> 423.69579
B22: 4 | C22: Number of transactions | D22: 28691 | F22: ='[1]Summary Sheet'!F25 -> 24683 | H22: =SUM(F22-D22)*100/D22 -> -13.969537 | I22: ='Summary Sheet'!I25 -> 51614 | K22: =SUM(I22-F22)*100/F22 -> 109.10748
B23: 5 | C23: Number of Scrips Traded | D23: 147 | F23: ='[1]Summary Sheet'!F26 -> 144 | I23: ='Summary Sheet'!I26 -> 161 | K23: =SUM(I23-F23)*100/F23 -> 11.805556
B24: 6 | C24: Number of Companies Listed | D24: 214 | F24: ='[1]Summary Sheet'!F27 -> 221 | I24: ='Summary Sheet'!I27 -> 234 | K24: =SUM(I24-F24)*100/F24 -> 5.8823529
B25: 7 | C25: Total Paid Up Value of Listed Share | E25: 106449 | G25: ='[1]Summary Sheet'!G28 -> 113971 | H25: =SUM(G25-E25)*100/E25 -> 7.0662947 | J25: ='Summary Sheet'!J28 -> 136817 | K25: =SUM(J25-G25)*100/G25 -> 20.04545
B26: 8 | C26: Total Number of Listed Securities | D26: 1098471 | F26: ='[1]Summary Sheet'!F29 -> 1178912 | H26: =SUM(F26-D26)*100/D26 -> 7.3229971 | I26: ='Summary Sheet'!I29 -> 1418105 | K26: =SUM(I26-F26)*100/F26 -> 20.289301
B27: 9 | C27: Market Capitalization | E27: 300428.79 | G27: ='[1]Summary Sheet'!G30 -> 471521.04 | H27: =SUM(G27-E27)*100/E27 -> 56.949352 | J27: ='Summary Sheet'!J30 -> 799760.34 | K27: =SUM(J27-G27)*100/G27 -> 69.612864
B28: 10 | C28: NEPSE Index at the end of Month
B29: - | C29: High | E29: 324.41 | G29: ='[1]Summary Sheet'!G32 -> 501.52 | H29: =SUM(G29-E29)*100/E29 -> 54.594495 | J29: ='Summary Sheet'!J32 -> 806.66 | K29: =SUM(J29-G29)*100/G29 -> 60.843037
B30: - | C30: Low | E30: 312.5 | G30: ='[1]Summary Sheet'!G33 -> 481.94 | H30: =SUM(G30-E30)*100/E30 -> 54.2208 | J30: ='Summary Sheet'!J33 -> 754.09 | K30: =SUM(J30-G30)*100/G30 -> 56.469685
B31: - | C31: Closing | E31: 323.62 | G31: ='[1]Summary Sheet'!G34 -> 497.24 | H31: =SUM(G31-E31)*100/E31 -> 53.649342 | J31: ='Summary Sheet'!J34 -> 787.05 | K31: =SUM(J31-G31)*100/G31 -> 58.283726
B32: 11 | C32: Market Capitalization of Group -A | E32: 260732.4 | G32: ='[1]Summary Sheet'!G35 -> 412442.43 | H32: =SUM(G32-E32)*100/E32 -> 58.186106 | J32: ='Summary Sheet'!J35 -> 647127.66 | K32: =SUM(J32-G32)*100/G32 -> 56.90133
B33: 12 | C33: NEPSE Sensitive Index
B34: - | C34: High | E34: 80.48 | G34: ='[1]Summary Sheet'!G37 -> 127.25 | H34: =SUM(G34-E34)*100/E34 -> 58.113817 | J34: ='Summary Sheet'!J37 -> 201.62 | K34: =SUM(J34-G34)*100/G34 -> 58.444008
B35: - | C35: Low | E35: 77.4 | G35: ='[1]Summary Sheet'!G38 -> 122.82 | H35: =SUM(G35-E35)*100/E35 -> 58.682171 | J35: ='Summary Sheet'!J38 -> 186.42 | K35: =SUM(J35-G35)*100/G35 -> 51.783097
B36: - | C36: Closing | E36: 80.29 | G36: ='[1]Summary Sheet'!G39 -> 126.51 | H36: =SUM(G36-E36)*100/E36 -> 57.566322 | J36: ='Summary Sheet'!J39 -> 193.38 | K36: =SUM(J36-G36)*100/G36 -> 52.857482
B37: 13 | C37: NEPSE Float Index at the end of Month
B38: - | C38: High | E38: 25.87 | G38: ='[1]Summary Sheet'!G41 -> 35.49 | H38: =SUM(G38-E38)*100/E38 -> 37.18593 | J38: ='Summary Sheet'!J41 -> 47.28 | K38: =SUM(J38-G38)*100/G38 -> 33.220626
B39: - | C39: Low | E39: 24.89 | G39: ='[1]Summary Sheet'!G42 -> 34.28 | H39: =SUM(G39-E39)*100/E39 -> 37.725994 | J39: ='Summary Sheet'!J42 -> 44.17 | K39: =SUM(J39-G39)*100/G39 -> 28.850642
B40: - | C40: Closing | E40: 25.69 | G40: ='[1]Summary Sheet'!G43 -> 34.98 | H40: =SUM(G40-E40)*100/E40 -> 36.161931 | J40: ='Summary Sheet'!J43 -> 45.74 | K40: =SUM(J40-G40)*100/G40 -> 30.760435
B41: 14 | C41: Bond Market (Total Listed)
B42: i | C42: Government Bond | D42: 349409 | E42: 34940.9 | F42: 449409 | G42: 44940.9 | H42: =SUM(F42-D42)*100/D42 -> 28.619755 | I42: 434409 | J42: 43440.9 | K42: =SUM(J42-G42)*100/G42 -> -3.3377169
B43: ii | C43: Corporate Bond | D43: 5735 | E43: 5735 | F43: 6135 | G43: 6135 | H43: =SUM(G43-D43)*100/D43 -> 6.9747167 | I43: 6597.37 | J43: =I43 -> 6597.37 | K43: =SUM(J43-G43)*100/G43 -> 7.5365933

Sheet Summary Sheet
A1: Comparative Summary Sheet of Transactions with Previous Months
A2: Dec 2013-Jan 2014
A3: Poush 2070
C5: Particulars | D5: Oct-Nov 2013 | F5: Nov-Dec 2013 | H5: Change | I5: Dec 2013-Jan 2014 | K5: Change
D6: Share units | E6: Amount | F6: Share units | G6: Amount | H6: in | I6: Share units | J6: Amount | K6: in
D7: ( '000 ) | E7: Rs. in million | F7: ( '000 ) | G7: Rs. in million | H7: % | I7: ( '000 ) | J7: Rs. in million | K7: %
B8: 1 | C8: Turnover | D8: =SUM(D9:D20) -> 5484.46 | E8: =SUM(E9:E20) -> 1884.89 | F8: =SUM(F9:F22) -> 19567.36 | G8: =SUM(G9:G22) -> 6653.72 | H8: =SUM(G8-E8)*100/E8 -> 253.00309 | I8: 18093.87 | J8: 8050.22 | K8: =SUM(J8-G8)*100/G8 -> 20.988259
B9: A | C9: Commercial Bank | D9: 3952.58 | E9: 1412.55 | F9: 11209.51 | G9: 4436.5 | H9: =SUM(G9-E9)*100/E9 -> 214.07738 | I9: 10445.33 | J9: 5393.14 | K9: =SUM(J9-G9)*100/G9 -> 21.562944
B10: B | C10: Finance | D10: 294.31 | E10: 42.72 | F10: 381.91 | G10: 77.09 | H10: =SUM(G10-E10)*100/E10 -> 80.45412 | I10: 550.01 | J10: 131.44 | K10: =SUM(J10-G10)*100/G10 -> 70.502011
B11: C | C11: Hotel | D11: 33.85 | E11: 9.22 | F11: 141.8 | G11: 44.53 | H11: =SUM(G11-E11)*100/E11 -> 382.9718 | I11: 100.26 | J11: 31.29 | K11: =SUM(J11-G11)*100/G11 -> -29.732764
B12: D | C12: Manufacturing & Processing | D12: 0.33 | E12: 0.75 | F12: 2.3 | G12: 4.8 | H12: =SUM(G12-E12)*100/E12 -> 540 | I12: 2.24 | J12: 4.19 | K12: =SUM(J12-G12)*100/G12 -> -12.708333
B13: E | C13: Other | D13: 90.9 | E13: 60.07 | F13: 98.79 | G13: 63.62 | H13: =SUM(G13-E13)*100/E13 -> 5.9097719 | I13: 244.39 | J13: 164 | K13: =SUM(J13-G13)*100/G13 -> 157.78057
B14: F | C14: Hydro Power | D14: 199.67 | E14: 173.8 | F14: 1101.44 | G14: 490.5 | H14: =SUM(G14-E14)*100/E14 -> 182.22094 | I14: 760.25 | J14: 547.05 | K14: =SUM(J14-G14)*100/G14 -> 11.529052
B15: G | C15: Trading | D15: 0 | E15: 0 | F15: 0.4 | G15: 0.69 | H15: 0 | I15: 1.03 | J15: 1.8 | K15: =SUM(J15-G15)*100/G15 -> 160.86957
B16: H | C16: Insurance | D16: 185.4 | E16: 78.73 | F16: 1132.78 | G16: 776.54 | H16: =SUM(G16-E16)*100/E16 -> 886.33304 | I16: 852.77 | J16: 830.77 | K16: =SUM(J16-G16)*100/G16 -> 6.9835424
B17: I | C17: Development Bank | D17: 549.07 | E17: 74.88 | F17: 2082.54 | G17: 525.52 | H17: =SUM(G17-E17)*100/E17 -> 601.81624 | I17: 2240.58 | J17: 573.12 | K17: =SUM(J17-G17)*100/G17 -> 9.0576952
B18: J | C18: Mutual Fund | D18: 1.1 | E18: 0.03 | F18: 2966.26 | G18: 34.03 | H18: =SUM(G18-E18)*100/E18 -> 113333.33 | I18: 2403.38 | J18: 30.5 | K18: =SUM(J18-G18)*100/G18 -> -10.3732
B19: K | C19: Preferred Stock | D19: 0.54 | E19: 0.38 | F19: 0 | G19: 0 | H19: =SUM(G19-E19)*100/E19 -> -100 | I19: 0.01 | J19: 0.01 | K19: 0
C20: Promotor Share | D20: 176.71 | E20: 31.76 | F20: 449.63 | G20: 199.9 | H20: =SUM(G20-E20)*100/E20 -> 529.40806 | I20: 493.64 | J20: 342.92 | K20: =SUM(J20-G20)*100/G20 -> 71.545773
C21: Corporate Bond
C22: Government Bond
B23: 2 | C23: Market days | D23: 19 | F23: 17 | I23: 19
B24: 3 | C24: Average daily turnover | D24: 288.65579 | E24: 99.204737 | F24: 1151.0212 | G24: 391.39529 | I24: =I8/I23 -> 952.30895 | J24: =J8/I23 -> 423.69579
B25: 4 | C25: Number of transactions | D25: 24683 | F25: 45962 | I25: 51614
B26: 5 | C26: Number of Scrips Traded | D26: 144 | F26: 160 | I26: 161
B27: 6 | C27: Number of Companies Listed | D27: 214 | F27: 235 | I27: ='Cumulative data'!I26 -> 234
B28: 7 | C28: Total Paid Up Value of Listed Share | E28: 104809 | G28: 134688 | H28: =SUM(G28-E28)*100/E28 -> 28.508048 | J28: ='Cumulative data'!J27 -> 136817 | K28: =SUM(J28-G28)*100/G28 -> 1.5806902
B29: 8 | C29: Total Number of Listed Securities | D29: 1082061 | F29: 1397818 | H29: =SUM(F29-D29)*100/D29 -> 29.181072 | I29: ='Cumulative data'!I28 -> 1418105 | K29: =SUM(I29-F29)*100/F29 -> 1.4513334
B30: 9 | C30: Market Capitalization | E30: 290340.48 | G30: 744141.31 | H30: =SUM(G30-E30)*100/E30 -> 156.29954 | J30: ='Cumulative data'!J29 -> 799760.34 | K30: =SUM(J30-G30)*100/G30 -> 7.4742568
B31: 10 | C31: NEPSE Index at the end of Month
B32: - | C32: High | E32: 501.52 | G32: 732.95 | H32: =SUM(G32-E32)*100/E32 -> 46.145717 | J32: 806.66 | K32: =SUM(J32-G32)*100/G32 -> 10.056621
B33: - | C33: Low | E33: 481.94 | G33: 633.99 | H33: =SUM(G33-E33)*100/E33 -> 31.54957 | J33: 754.09 | K33: =SUM(J33-G33)*100/G33 -> 18.943516
B34: - | C34: Closing | E34: 316.27 | G34: 732.95 | H34: =SUM(G34-E34)*100/E34 -> 131.74819 | J34: 787.05 | K34: =SUM(J34-G34)*100/G34 -> 7.381131
B35: 11 | C35: Market Capitalization of Group -A | E35: 251359.31 | G35: 607989.63 | H35: =SUM(G35-E35)*100/E35 -> 141.88069 | J35: ='Cumulative data'!J34 -> 647127.66 | K35: =SUM(J35-G35)*100/G35 -> 6.4372852
B36: 12 | C36: NEPSE Sensitive Index
B37: - | C37: High | E37: 127.25 | G37: 181.98 | H37: =SUM(G37-E37)*100/E37 -> 43.009823 | J37: 201.62 | K37: =SUM(J37-G37)*100/G37 -> 10.792395
B38: - | C38: Low | E38: 122.82 | G38: 158.47 | H38: =SUM(G38-E38)*100/E38 -> 29.026217 | J38: 186.42 | K38: =SUM(J38-G38)*100/G38 -> 17.637408
B39: - | C39: Closing | E39: 78.42 | G39: 181.98 | H39: =SUM(G39-E39)*100/E39 -> 132.05815 | J39: 193.38 | K39: =SUM(J39-G39)*100/G39 -> 6.2644247
B40: 13 | C40: NEPSE Sensitive Float Index at the end of Month
B41: - | C41: High | E41: 35.49 | G41: 43.22 | H41: =SUM(G41-E41)*100/E41 -> 21.780783 | J41: 47.28 | K41: =SUM(J41-G41)*100/G41 -> 9.3937992
B42: - | C42: Low | E42: 34.28 | G42: 38 | H42: =SUM(G42-E42)*100/E42 -> 10.851809 | J42: 44.17 | K42: =SUM(J42-G42)*100/G42 -> 16.236842
B43: - | C43: Closing | E43: 25.19 | G43: 43.22 | H43: =SUM(G43-E43)*100/E43 -> 71.576022 | J43: 45.74 | K43: =SUM(J43-G43)*100/G43 -> 5.830634
C44: Note:- US $ 1 =Rs. 99.21 (23 Jan 2014)
B46: Listing on Jul/Aug 2013
B47: SN | C47: Name of Companies | D47: Type of Securities | E47: Listed Sucurities in '000' | F47: Amount Rs. in million | G47: Listed Date
B48: 1 | C48: NEPAL CREDIT & COM. BANK LTD. | D48: BONUS | E48: 700 | F48: =E48/10 -> 70 | G48: 2070-4-15
B49: 2 | C49: NEPAL INSURANCE CO LTD. | D49: BONUS | E49: 219.24 | F49: =E49/10 -> 21.924 | G49: 2070-4-15
B50: 3 | C50: SHIKHAR INSURANCE CO. LTD. | D50: BONUS | E50: 500 | F50: =E50/10 -> 50 | G50: 2070-4-15
B51: 4 | C51: NEPAL LIFE INSURANCE CO. LTD. | D51: BONUS | E51: 2625 | F51: =E51/10 -> 262.5 | G51: 2070-4-15
B52: 5 | C52: PRUDENTIAL INSURANCE CO LTD. | D52: BONUS | E52: 250 | F52: =E52/10 -> 25 | G52: 2070-4-15
B53: 6 | C53: SWABALAMBAN LAGHUBITTA BIKAS BANK | D53: BONUS | E53: 66.7 | F53: =E53/10 -> 6.67 | G53: 2070-4-15
B54: 7 | C54: LUMBINI GENERAL INSURANCE CO LTD. | D54: BONUS | E54: 127.84 | F54: =E54/10 -> 12.784 | G54: 2070-4-30
B55: 8 | C55: OM FINANCE LTD. | D55: BONUS | E55: 246.75 | F55: =E55/10 -> 24.675 | G55: 2070-4-30
B56: 9 | C56: GURAS LIFE INSURANCE CO LTD. | D56: BONUS | E56: 234 | F56: =E56/10 -> 23.4 | G56: 2070-4-30
B57: 10 | C57: SAHAYOGI BIKAS BANK LD. | D57: BONUS | E57: 234 | F57: =E57/10 -> 23.4 | G57: 2070-4-30
B58: 11 | C58: NIRDHAN UTTHAN BANK LTD. | D58: BONUS | E58: 75.35 | F58: =E58/10 -> 7.535 | G58: 2070-4-30
B59: 12 | C59: HIMALAYAN BANK LTD. | D59: BONUS | E59: 3600 | F59: =E59/10 -> 360 | G59: 2070-4-30
B60: 13 | C60: PASCHIMANCHAL FINANCE LTD. | D60: BONUS | E60: 392.73 | F60: =E60/10 -> 39.273 | G60: 2070-4-30
C61: Total | E61: =SUM(E48:E60) -> 9271.61 | F61: =SUM(F48:F60) -> 927.161
B62: 1 | C62: NEPAL CREDIT & COM. BANK LTD. | D62: RIGHTS | E62: 21.8 | F62: =E62/10 -> 2.18 | G62: 2070-4-15
B63: 2 | C63: GLOBAL IME BANK LTD. | D63: MERGE | E63: 1655.8 | F63: =E63/10 -> 165.58 | G63: 2070-4-21
C64: Total | E64: =SUM(E62:E63) -> 1677.6 | F64: =SUM(F62:F63) -> 167.76
C65: Grand Total | E65: =E64+E61 -> 10949.21 | F65: =F64+F61 -> 1094.921
B69: Listing on Aug-Sept 2013
B70: SN | C70: Name of Companies | D70: Type of Securities | E70: Listed Sucurities in '000' | F70: Amount Rs. in million | G70: Listed Date
B71: 1 | C71: MEGA BANK NEPAL LTD. | D71: ORDINARY | E71: 23300 | F71: =E71/10 -> 2330 | G71: 2070-5-4
B72: 2 | C72: SINDHU BIKAS BANK LTD. | D72: ORDINARY | E72: 1000 | F72: =E72/10 -> 100 | G72: 2070-5-4
B73: 3 | C73: JHIMRUK BIKAS BANK LTD. | D73: ORDINARY | E73: 400 | F73: =E73/10 -> 40 | G73: 2070-5-4
B74: 4 | C74: GAUMUKHI BIKAS BANK LTD. | D74: ORDINARY | E74: 400 | F74: =E74/10 -> 40 | G74: 2070-5-26
B75: 5 | C75: NAMASTE BITTIYA SANTHA LTD. | D75: ORDINARY | E75: 250 | F75: =E75/10 -> 25 | G75: 2070-5-26
B76: 6 | C76: MISSION DEV. BANK LTD. | D76: ORDINARY | E76: 1000 | F76: =E76/10 -> 100 | G76: 2070-5-26
B77: 7 | C77: AGRICULTURE DEV. BANK LTD. | D77: ADD. SHARE | E77: 1555 | F77: =E77/10 -> 155.5 | G77: 2070-5-21
C78: Total | E78: =SUM(E71:E77) -> 27905 | F78: =SUM(F71:F77) -> 2790.5
B79: 1 | C79: NECO INSURANCE CO. LTD. | D79: BONUS | E79: 139.46 | F79: =E79/10 -> 13.946 | G79: 2070-5-21
B80: 2 | C80: SAGARMATHA INSURANCE CO. LTD. | D80: BONUS | E80: 1292.06 | F80: =E80/10 -> 129.206 | G80: 2070-5-21
B81: 3 | C81: GOODWILL FINANCE LTD. | D81: BONUS | E81: 104.83 | F81: =E81/10 -> 10.483 | G81: 2070-5-21
B82: 4 | C82: SALT TRADING CO. LTD. | D82: BONUS | E82: 53.74 | F82: =E82/10 -> 5.374 | G82: 2070-5-21
B83: 5 | C83: JANAKI FINANCE LTD. | D83: BONUS | E83: 48.75 | F83: =E83/10 -> 4.875 | G83: 2070-5-21
C84: Total | E84: =SUM(E79:E83) -> 1638.84 | F84: =SUM(F79:F83) -> 163.884
C85: Grand Total | E85: =E84+E78 -> 29543.84 | F85: =F84+F78 -> 2954.384
B89: Listing on Sept-Oct 2013
B90: SN | C90: Name of Companies | D90: Type of Securities | E90: Listed Sucurities in '000' | F90: Amount Rs. in million | G90: Listed Date
B91: 1 | C91: HAMRO BIKAS BANK LTD. | D91: ORDINARY | E91: 601 | F91: =E91/10 -> 60.1 | G91: 2070-6-8
B92: 2 | C92: RURAL MICRO FINANCE DEV. CENTRE LTD. | D92: ORDINARY | E92: 5200 | F92: =E92/10 -> 520 | G92: 2070-6-8
B93: 3 | C93: JEBIL'S FINANCE LTD. | D93: ORDINARY | E93: 2000 | F93: =E93/10 -> 200 | G93: 2070-6-8
B94: 4 | C94: SANA KISAN BIKAS BANK LTD. | D94: ORDINARY | E94: 2000 | F94: =E94/10 -> 200 | G94: 2070-6-8
C95: Total | E95: =SUM(E91:E94) -> 9801 | F95: =SUM(F91:F94) -> 980.1
B96: 1 | C96: ALIANCE INSURANE CO LTD. | D96: BONUS | E96: 147.72 | F96: =E96/10 -> 14.772 | G96: 2070-6-6
C97: Total | E97: =E96 -> 147.72 | F97: =F96 -> 14.772
B99: 1 | C99: NEPAL BANK LTD. | D99: RIGHTS | E99: 35851.41 | F99: =E99/10 -> 3585.141 | G99: 2070-6-15
C100: Total | E100: =E99 -> 35851.41 | F100: =F99 -> 3585.141
C101: Grand Total | E101: =E100+E95+E97 -> 45800.13 | F101: =F100+F95+F97 -> 4580.013
B104: Listing on Dec 2013-Jan 2014
B105: SN | C105: Name of Companies | D105: Type of Securities | E105: Listed Sucurities in '000' | F105: Amount Rs. in million | G105: Listed Date
B106: 1 | C106: Sanima Mai Hydropower Ltd. | D106: ORDINARY | E106: 10550 | F106: =E106/10 -> 1055 | G106: 2070-9-29
C107: Total | E107: =SUM(E106:E106) -> 10550 | F107: =SUM(F106:F106) -> 1055
B108: 1 | C108: NLG Insurance Co. Ltd. | D108: BONUS | E108: 450 | F108: =E108/10 -> 45 | G108: 2070-9-5
C109: Bank Of Kathmandu Ltd. | D109: BONUS | E109: 2358.16 | F109: =E109/10 -> 235.816 | G109: 2070-9-18
C110: City Development Bank Ltd. | D110: BONUS | E110: 542.68 | F110: =E110/10 -> 54.268 | G110: 2070-9-29
C111: Total | E111: =E108 -> 450 | F111: =F108 -> 45
...

Sheet Companywise Transaction
A1: Company wise Transactions
A2: Dec-Jan 2014
A3: Poush- 2070
B4: Commercial Bank
B5: Name of the company | C5: Traded Share | D5: Traded | E5: Number | J5: Trading
C6: Quantity | D6: Amount | E6: Of | F6: High | G6: Low | H6: Closing | I6: Average | J6: Days
C7: ( in '000) | D7: Rs. In million | E7: Trades | I7: Price
A8: 1 | B8: Agriculture Development Bank Limited | C8: 530.36 | D8: 251.108 | E8: 2937 | F8: 518 | G8: 416 | H8: 501 | I8: 473.47 | J8: 19
A9: 2 | B9: Bank of Kathmandu | C9: 318.77 | D9: 213.82 | E9: 1084 | F9: 742 | G9: 618 | H9: 644 | I9: 670.76 | J9: 19
A10: 3 | B10: Citizens Bank International Limited | C10: 255.12 | D10: 115.13 | E10: 1130 | F10: 502 | G10: 400 | H10: 453 | I10: 451.28 | J10: 19
A11: 4 | B11: Everest Bank Ltd | C11: 106.72 | D11: 238.781 | E11: 677 | F11: 2360 | G11: 2055 | H11: 2210 | I11: 2237.52 | J11: 19
A12: 5 | B12: GRAND Bank Ltd. | C12: 314.38 | D12: 100.71 | E12: 818 | F12: 360 | G12: 285 | H12: 304 | I12: 320.35 | J12: 19
A13: 6 | B13: Himalayan Bank Ltd. | C13: 80.77 | D13: 72.365 | E13: 377 | F13: 973 | G13: 840 | H13: 890 | I13: 895.96 | J13: 19
A14: 7 | B14: Janata Bank Nepal Ltd. | C14: 289.19 | D14: 89.55 | E14: 833 | F14: 350 | G14: 276 | H14: 302 | I14: 309.66 | J14: 19
A15: 8 | B15: Kumari Bank Ltd | C15: 779.61 | D15: 408.407 | E15: 1622 | F15: 593 | G15: 463 | H15: 579 | I15: 523.86 | J15: 19
A16: 9 | B16: KIST Bank Limited | C16: 888.89 | D16: 219.492 | E16: 1276 | F16: 267 | G16: 221 | H16: 234 | I16: 246.93 | J16: 19
A17: 10 | B17: Laxmi Bank Limited | C17: 262.52 | D17: 140.413 | E17: 700 | F17: 584 | G17: 488 | H17: 522 | I17: 534.87 | J17: 19
A18: 11 | B18: Machhachapuchhre Bank Ltd | C18: 539.49 | D18: 231.521 | E18: 1141 | F18: 484 | G18: 368 | H18: 480 | I18: 429.15 | J18: 19
A19: 12 | B19: Mega Bank Nepal Ltd. | C19: 326.29 | D19: 136.847 | E19: 3063 | F19: 475 | G19: 367 | H19: 444 | I19: 419.41 | J19: 19
... A32: 25 | B32: Sunrise Bank Limited | C32: 272.97 | D32: 115.94 | E32: 1288 | F32: 460 | G32: 369 | H32: 445 | I32: 424.74 | J32: 19
A33: 27 | B33: Total | C33: 10445.34 | D33: 5393.138 | E33: 29244
B36: Hotel
B37: Name of the company | C37: Traded Share | D37: Traded | E37: Number | J37: Trading
C38: Quantity | D38: Amount | E38: Of | F38: High | G38: Low | H38: Closing | I38: Average | J38: Days
C39: ( in '000) | D39: Rs. In million | E39: Trades | I39: Price
A40: 1 | B40: Oriental Hotel Ltd. | C40: 27.11 | D40: 7.645 | E40: 185 | F40: 330 | G40: 238 | H40: 290 | I40: 281.99 | J40: 16
A41: 2 | B41: Soaltee Hotel Ltd. | C41: 112.87 | D41: 36.67 | E41: 52 | F41: 375 | G41: 285 | H41: 340 | I41: 324.9 | J41: 11
A42: 3 | B42: Taragaon Regency Hotel | C42: 1.82 | D42: 0.217 | E42: 42 | F42: 130 | G42: 113 | H42: 130 | I42: 119.29 | J42: 10
B43: Total | C43: 141.8 | D43: 44.532 | E43: 279
B46: Mutual Fund
B47: Name of the company | C47: Traded Share | D47: Traded | E47: Number | J47: Trading
C48: Quantity | D48: Amount | E48: Of | F48: High | G48: Low | H48: Closing | I48: Average | J48: Days
C49: ( in '000) | D49: Rs. In million | E49: Trades | I49: Price
A50: 1 | B50: Nabil Balance Fund 1 | C50: 1723.59 | D50: 18.978 | E50: 385 | F50: 12.1 | G50: 10.1 | H50: 11.37 | I50: 11.01 | J50: 17
A51: 2 | B51: Siddhartha Investment Growth Scheme-1 | C51: 1242.67 | D51: 15.056 | E51: 118 | F51: 12.75 | G51: 11.3 | H51: 12 | I51: 12.12 | J51: 16
B52: Total | C52: 2966.26 | D52: 34.034 | E52: 503
B54: Others
B55: Name of the company | C55: Traded Share | D55: Traded | E55: Number | J55: Trading
C56: Quantity | D56: Amount | E56: Of | F56: High | G56: Low | H56: Closing | I56: Average | J56: Days
C57: ( in '000) | D57: Rs. In million | E57: Trades | I57: Price
A58: 1 | B58: Nepal Doorsanchar Company Limited | C58: 98.79 | D58: 63.619 | E58: 392 | F58: 689 | G58: 612 | H58: 652 | I58: 644.01 | J58: 17
B59: Total | C59: 98.79 | D59: 63.619 | E59: 392
B62: Manufacturing & Processing
B63: Name of the company | C63: Traded Share | D63: Traded | E63: Number | J63: Trading
C64: Quantity | D64: Amount | E64: Of | F64: High | G64: Low | H64: Closing | I64: Average | J64: Days
C65: ( in '000) | D65: Rs. In million | E65: Trades | I65: Price
A66: 1 | B66: Bottlers Nepal (Terai)Ltd. | C66: 2.1 | D66: 3.747 | E66: 3 | F66: 1785 | G66: 1751 | H66: 1751 | I66: 1784.19 | J66: 2
A67: 2 | B67: Himalayan Distillery Ltd. | C67: 0.1 | D67: 0.01 | E67: 1 | F67: 99 | G67: 99 | H67: 99 | I67: 99 | J67: 1
A68: 3 | B68: Uniliver Nepal Ltd. | C68: 0.1 | D68: 1.044 | E68: 4 | F68: 10500 | G68: 10290 | H68: 10290 | I68: 10437 | J68: 3
B69: Total | C69: 2.3 | D69: 4.801 | E69: 8
B72: Hydro Power
B73: Name of the company | C73: Traded Share | D73: Traded | E73: Number | J73: Trading
C74: Quantity | D74: Amount | E74: Of | F74: High | G74: Low | H74: Closing | I74: Average | J74: Days
C75: ( in '000) | D75: Rs. In million | E75: Trades | I75: Price
A76: 1 | B76: Arun Valley Hydropower Development Co. Ltd. | C76: 300.48 | D76: 169.622 | E76: 633 | F76: 610 | G76: 531 | H76: 580 | I76: 564.51 | J76: 19
A77: 2 | B77: Butwal Power Co. Ltd. | C77: 74.75 | D77: 88.468 | E77: 207 | F77: 1320 | G77: 1090 | H77: 1320 | I77: 1183.49 | J77: 19
A78: 3 | B78: Chilime Hydro power Co. | C78: 177.33 | D78: 271.548 | E78: 913 | F78: 1665 | G78: 1435 | H78: 1511 | I78: 1531.31 | J78: 19
A79: 4 | B79: National Hydro Power Co. | C79: 207.69 | D79: 17.411 | E79: 187 | F79: 96 | G79: 77 | H79: 83 | I79: 83.83 | J79: 18
B80: Total | C80: 760.25 | D80: 547.049 | E80: 1940
B82: Insurance
B83: Name of the company | C83: Traded Share | D83: Traded | E83: Number | J83: Trading
C84: Quantity | D84: Amount | E84: Of | F84: High | G84: Low | H84: Closing | I84: Average | J84: Days
C85: ( in '000) | D85: Rs. In million | E85: Trades | I85: Price
A86: 1 | B86: Company Name | C86: Share Quantity(in '000) | D86: Amount(in '000000) | E86: Number Of Trades | F86: High | G86: Low | H86: Closing | I86: Average Price | J86: Trading Days
A87: 2 | B87: Alliance Insurance Company Limited | C87: 81.33 | D87: 35.488 | E87: 136 | F87: 507 | G87: 395 | H87: 501 | I87: 436.33 | J87: 18
A88: 3 | B88: Asian Life Insurance Co. Limited | C88: 95.37 | D88: 62.7 | E88: 506 | F88: 719 | G88: 615 | H88: 710 | I88: 657.41 | J88: 19
A89: 4 | B89: Guras Life Insurance Co. Ltd. | C89: 44.33 | D89: 15.043 | E89: 228 | F89: 393 | G89: 307 | H89: 373 | I89: 339.34 | J89: 19
A90: 5 | B90: Himalayan Gen.Insu. Co.Ltd. | C90: 25.89 | D90: 14.954 | E90: 99 | F90: 718 | G90: 290 | H90: 318 | I90: 577.57 | J90: 14
A91: 6 | B91: Lumbini General Insurance | C91: 40.02 | D91: 14.419 | E91: 223 | F91: 409 | G91: 308 | H91: 352 | I91: 360.27 | J91: 18
A92: 7 | B92: Life Insurance Co. Nepal | C92: 37.46 | D92: 92.667 | E92: 253 | F92: 2760 | G92: 1990 | H92: 2630 | I92: 2474.02 | J92: 19
A93: 8 | B93: NB Insurance Co. Ltd. | C93: 0.86 | D93: 0.068 | E93: 7 | F93: 81 | G93: 78 | H93: 80 | I93: 79.5 | J93: 4
A94: 9 | B94: Nepal Insurance Co.Ltd. | C94: 13.5 | D94: 7.179 | E94: 33 | F94: 572 | G94: 509 | H94: 530 | I94: 531.71 | J94: 14
A95: 10 | B95: NLG Insurance Company Ltd. | C95: 91.14 | D95: 61.31 | E95: 1349 | F95: 760 | G95: 628 | H95: 710 | I95: 672.68 | J95: 18
A96: 11 | B96: Nepal Life Insurance Co. Ltd. | C96: 45.55 | D96: 156.755 | E96: 372 | F96: 3700 | G96: 3060 | H96: 3550 | I96: 3441.31 | J96: 19
A97: 12 | B97: National LifeInsu. Co.Ltd. | C97: 135.48 | D97: 229.354 | E97: 347 | F97: 2000 | G97: 1520 | H97: 1910 | I97: 1692.86 | J97: 19
A98: 13 | B98: Prudential Insurance Co. | C98: 12.84 | D98: 4.548 | E98: 50 | F98: 465 | G98: 268 | H98: 290 | I98: 354.32 | J98: 14
... A104: 19 | B104: Surya Life Insurance Company Limited | C104: 66.19 | D104: 27.613 | E104: 335 | F104: 455 | G104: 375 | H104: 448 | I104: 417.2 | J104: 19
B105: United Insurance Co.(Nepal)Ltd. | C105: 34.5 | D105: 10.03 | E105: 110 | F105: 310 | G105: 262 | H105: 306 | I105: 290.71 | J105: 16
B106: Total | C106: 852.76 | D106: 830.767 | E106: 4815
B108: Name of the company | C108: Traded Share | D108: Traded | E108: Number | J108: Trading
C109: Quantity | D109: Amount | E109: Of | F109: High | G109: Low | H109: Closing | I109: Average | J109: Days
C110: ( in '000) | D110: Rs. In million | E110: Trades | I110: Price
A111: 1 | B111: Citizen Investment Trust | C111: 6.73 | D111: 14.309 | E111: 94 | F111: 2320 | G111: 2000 | H111: 2130 | I111: 2127.05 | J111: 16
A112: 2 | B112: Everest Finance Ltd, | C112: 1.02 | D112: 0.114 | E112: 7 | F112: 118 | G112: 110 | H112: 118 | I112: 111.78 | J112: 5
A113: 3 | B113: Fewa Finance Co. Ltd. | C113: 4.03 | D113: 1.05 | E113: 16 | F113: 265 | G113: 232 | H113: 262 | I113: 260.8 | J113: 8
A114: 4 | B114: Goodwill Finance Co. Ltd. | C114: 0.95 | D114: 0.129 | E114: 7 | F114: 138 | G114: 134 | H114: 134 | I114: 135.96 | J114: 5
A115: 5 | B115: Hama Merchant & Finance Ltd. | C115: 32.94 | D115: 3.733 | E115: 226 | F115: 126 | G115: 80 | H115: 120 | I115: 113.31 | J115: 15
A116: 6 | B116: ICFC Bittya Sanstha Ltd. | C116: 31.91 | D116: 7.196 | E116: 101 | F116: 233 | G116: 212 | H116: 230 | I116: 225.5 | J116: 18
A117: 7 | B117: International Leasing And Fin. Co. | C117: 327.34 | D117: 73.849 | E117: 384 | F117: 247 | G117: 195 | H117: 232 | I117: 225.6 | J117: 19
A118: 8 | B118: Janaki Finance Ltd. | C118: 9.95 | D118: 2.301 | E118: 38 | F118: 239 | G118: 226 | H118: 235 | I118: 231.37 | J118: 15
A119: 9 | B119: Kaski Finance Limited | C119: 11.42 | D119: 1.513 | E119: 72 | F119: 144 | G119: 128 | H119: 139 | I119: 132.44 | J119: 18
A120: 10 | B120: Kathmandu Finance Limited. | C120: 0.31 | D120: 0.044 | E120: 5 | F120: 144 | G120: 142 | H120: 144 | I120: 142.08 | J120: 1
A121: 11 | B121: Lumbini Finance Ltd. | C121: 5.65 | D121: 0.962 | E121: 55 | F121: 195 | G121: 145 | H121: 173 | I121: 170.13 | J121: 14
A122: 12 | B122: Maha Laxmi Finance Ltd. | C122: 2.48 | D122: 0.421 | E122: 10 | F122: 180 | G122: 162 | H122: 180 | I122: 169.73 | J122: 4
... A137: 27 | B137: Zenith Finance Limited | C137: 15.42 | D137: 1.731 | E137: 132 | F137: 127 | G137: 100 | H137: 112 | I137: 112.25 | J137: 9
B138: Total | C138: 550.04 | D138: 131.442 | E138: 1639
B140: Development Bank | J140: Trading
B141: Name of the company | C141: Traded Share | D141: Traded | E141: Number | J141: Days
C142: Quantity | D142: Amount | E142: Of | F142: High | G142: Low | H142: Closing | I142: Average
C143: ( in '000) | D143: Rs. In million | E143: Trades | I143: Price | J143: 15
...

Sheet Transaction of Promotor share
A1: Company wise Transactions of Promotor Share
A2: Dec-Jan 2014
A3: Poush 2070
B4: Promotor Share Transaction
B5: Name of the company | C5: Traded Share | D5: Traded | E5: Number | J5: Trading
C6: Quantity | D6: Amount | E6: of | F6: High | G6: Low | H6: Closing | I6: Average | J6: Days
C7: ( in '000) | D7: Rs.in million | E7: Trades | I7: Price
A8: 1 | B8: Alliance Insurance Company Ltd. Promoter | C8: 14.94 | D8: 1.494 | E8: 1 | F8: 100 | G8: 100 | H8: 100 | I8: 100 | J8: 1
A9: 2 | B9: Citizens Bank International Limited Promoter Share | C9: 46.38 | D9: 163.132 | E9: 5 | F9: 135 | G9: 133 | H9: 133 | I9: 3517.53 | J9: 2
A10: 3 | B10: Kailash Bikas Bank Ltd. Promoter Share | C10: 23 | D10: 4.048 | E10: 4 | F10: 176 | G10: 176 | H10: 176 | I10: 176 | J10: 1
A11: 4 | B11: Kumari Bank Limited Promotor Share | C11: 23.33 | D11: 2.333 | E11: 2 | F11: 100 | G11: 100 | H11: 100 | I11: 100 | J11: 2
A12: 5 | B12: NABIL Bank Limited Promotor Share | C12: 91.91 | D12: 119.523 | E12: 119 | F12: 1455 | G12: 1275 | H12: 1300 | I12: 1300.42 | J12: 18
A13: 6 | B13: Nepal Express Finance Limited Promoter Share | C13: 35.67 | D13: 3.639 | E13: 1 | F13: 102 | G13: 102 | H13: 102 | I13: 102 | J13: 1
A14: 7 | B14: National Life Insurance Co. Ltd. Promoter Share | C14: 20.08 | D14: 12.312 | E14: 2 | F14: 620 | G14: 608 | H14: 608 | I14: 613.13 | J14: 2
A15: 8 | B15: Nepal Life Insurance Co. Ltd. Promoter | C15: 1.88 | D15: 3.234 | E15: 1 | F15: 1725 | G15: 1725 | H15: 1725 | I15: 1725 | J15: 1
A16: 9 | B16: Prime Commercial Bank Ltd. Promoter Share | C16: 208.4 | D16: 30.382 | E16: 18 | F16: 148 | G16: 143 | H16: 148 | I16: 145.78 | J16: 5
A17: 10 | B17: Seti Finance Ltd. Promoter Share | C17: 19.45 | D17: 1.945 | E17: 8 | F17: 100 | G17: 100 | H17: 100 | I17: 100 | J17: 2
A18: 11 | B18: Subbecha Bikas Bank Ltd. Promoter | C18: 8.6 | D18: 0.877 | E18: 1 | F18: 102 | G18: 102 | H18: 102 | I18: 102 | J18: 1
B19: Total | C19: 493.64 | D19: 342.919 | E19: 162

Sheet Market Capitalization
A2: Sectorwise Market Capitalization
A3: Dec-Jan 2014
A4: Date | B4: Com. | C4: Manufact- | D4: Hotel | E4: Others | F4: Hydro | G4: Trading | H4: Insurance | I4: Finance | J4: Dev. | K4: Total
B5: Bank | C5: & Pros. | F5: Power | J5: Bank | K5: Rs. in millions
A6: 41624 | B6: 462958.76 | C6: 16388.025 | D6: 14334.7 | E6: 100518.42 | F6: 50688.359 | G6: 981.77238 | H6: 60887.792 | I6: 27675.861 | J6: 48238.388 | K6: 782672.08
A7: 41626 | B7: 490132.48 | C7: 16388.025 | D7: 14550.397 | E7: 105018.42 | F7: 52680.372 | G7: 998.47999 | H7: 61940.428 | I7: 28220.664 | J7: 49052.139 | K7: 818981.41
A8: 41627 | B8: 487195.15 | C8: 16388.025 | D8: 14976.531 | E8: 105018.42 | F8: 52607.928 | G8: 998.47999 | H8: 62831.014 | I8: 28771.542 | J8: 48859.083 | K8: 817646.17
A9: 41628 | B9: 487195.15 | C9: 16388.025 | D9: 14976.531 | E9: 105018.42 | F9: 52607.928 | G9: 998.47999 | H9: 62831.014 | I9: 27206.995 | J9: 51042.08 | K9: 818264.62
A10: 41630 | B10: 476799.25 | C10: 16388.025 | D10: 15152.041 | E10: 104718.42 | F10: 51455.473 | G10: 998.47999 | H10: 63795.614 | I10: 27388.139 | J10: 50945.771 | K10: 807641.22
A11: 41631 | B11: 454659.96 | C11: 16388.025 | D11: 15071.853 | E11: 99768.423 | F11: 50606.151 | G11: 998.47999 | H11: 65661.737 | I11: 27521.295 | J11: 50476.769 | K11: 781152.69
A12: 41632 | B12: 460106.72 | C12: 16388.025 | D12: 15046.853 | E12: 102018.42 | F12: 50686.297 | G12: 998.47999 | H12: 65993.396 | I12: 27706.357 | J12: 50505.27 | K12: 789449.82
A13: 41634 | B13: 468570.23 | C13: 16576.768 | D13: 15041.954 | E13: 102018.42 | F13: 51163.759 | G13: 998.47999 | H13: 66708.403 | I13: 27633.838 | J13: 51071.435 | K13: 799783.29
A14: 41637 | B14: 465008.8 | C14: 16576.768 | D14: 14665.733 | E14: 100518.42 | F14: 50648.441 | G14: 998.47999 | H14: 65288.02 | I14: 27616.02 | J14: 51121.549 | K14: 792442.23
A15: 41639 | B15: 457809.29 | C15: 16576.768 | D15: 14362.036 | E15: 100368.42 | F15: 49458.822 | G15: 998.47999 | H15: 65259.043 | I15: 27525.388 | J15: 50975.98 | K15: 783334.23
A16: 41640 | B16: 447748.52 | C16: 16576.768 | D16: 14401.936 | E16: 98268.423 | F16: 47921.49 | G16: 998.47999 | H16: 63099.775 | I16: 27471.31 | J16: 50306.184 | K16: 766792.88
A17: 41641 | B17: 452739.24 | C17: 16576.768 | D17: 14892.581 | E17: 100218.42 | F17: 48287.914 | G17: 998.47999 | H17: 64480.621 | I17: 27403.871 | J17: 50203.248 | K17: 775801.14
... A25: 41653 | B25: 463810.2 | C25: 16383.132 | D25: 15000.167 | E25: 100518.42 | F25: 50905.112 | G25: 991.60038 | H25: 70252.013 | I25: 28128.943 | J25: 53770.754 | K25: 799760.34

Sheet Index
A1: NEPSE Index
A2: Dec-Jan 2014
A3: Date | B3: Com. | C3: Manufact- | D3: Hotel | E3: Other | F3: Hydro | G3: Trading | H3: Insurance | I3: Finance | J3: Dev. | K3: NEPSE
B4: Bank | C4: & Pros. | F4: Power | J4: Bank | K4: INDEX
A5: 41624 | B5: 785.79454 | C5: 923.64679 | D5: 1084.3274 | E5: 787.14339 | F5: 1761.8477 | G5: 168.75001 | H5: 1951.6965 | I5: 316.3968 | J5: 422.43796 | K5: 770.89988
A6: 41626 | B6: 831.91735 | C6: 923.64679 | D6: 1100.6435 | E6: 822.38215 | F6: 1831.087 | G6: 171.62177 | H6: 1985.4377 | I6: 322.62511 | J6: 429.56421 | K6: 806.66308
A7: 41627 | B7: 826.93173 | C7: 923.64679 | D7: 1132.8778 | E7: 822.38215 | F7: 1828.5689 | G7: 171.62177 | H7: 2013.9845 | I7: 328.92288 | J7: 427.87356 | K7: 805.34793
A8: 41628 | B8: 826.93173 | C8: 923.64679 | D8: 1132.8778 | E8: 822.38215 | F8: 1828.5689 | G8: 171.62177 | H8: 2013.9845 | I8: 318.10443 | J8: 436.62629 | K8: 805.34859
A9: 41630 | B9: 809.28644 | C9: 923.64679 | D9: 1146.154 | E9: 820.0329 | F9: 1788.5114 | G9: 171.62177 | H9: 2044.9038 | I9: 320.218 | J9: 435.76402 | K9: 794.88389
A10: 41631 | B10: 771.70872 | C10: 923.64679 | D10: 1140.0883 | E10: 781.27026 | F10: 1758.9903 | G10: 171.62177 | H10: 2104.7205 | I10: 321.77484 | J10: 431.73686 | K10: 768.81059
A11: 41632 | B11: 780.95368 | C11: 923.64679 | D11: 1138.1972 | E11: 798.88964 | F11: 1761.7761 | G11: 171.62177 | H11: 2115.3515 | I11: 323.9356 | J11: 431.63076 | K11: 776.90356
A12: 41634 | B12: 795.31906 | C12: 934.28457 | D12: 1137.8266 | E12: 798.88964 | F12: 1778.3719 | G12: 171.62177 | H12: 2138.2703 | I12: 323.08773 | J12: 436.46935 | K12: 787.07281
A13: 41637 | B13: 789.21323 | C13: 934.28457 | D13: 1109.3679 | E13: 787.14339 | F13: 1760.4603 | G13: 171.62177 | H13: 2081.5093 | I13: 322.8794 | J13: 435.99818 | K13: 779.49923
A14: 41639 | B14: 776.99421 | C14: 934.28457 | D14: 1086.3952 | E14: 785.96876 | F14: 1719.111 | G14: 171.62177 | H14: 2080.5854 | I14: 321.82092 | J14: 434.70564 | K14: 770.52978
A15: 41640 | B15: 759.91906 | C15: 934.28457 | D15: 1089.4134 | E15: 769.524 | F15: 1665.6757 | G15: 171.62177 | H15: 1999.4607 | I15: 321.03968 | J15: 428.99623 | K15: 754.08694
A16: 41641 | B16: 769.30809 | C16: 934.28457 | D16: 1126.5275 | E16: 784.79414 | F16: 1678.412 | G16: 171.62177 | H16: 2043.2159 | I16: 320.25157 | J16: 428.11842 | K16: 763.47427
... A24: 41653 | B24: 788.1202 | C24: 923.37102 | D24: 1134.6657 | E24: 787.14339 | F24: 1769.3817 | G24: 170.43928 | H24: 2226.0957 | I24: 328.72502 | J24: 458.54106 | K24: 787.05278

Sheet Sensitive M.Cap
A2: Sectorwise Sensitive Market Capitalization
A3: Dec- Jan 2014
A4: Date | B4: Com. | C4: Man. | D4: Hotel | E4: Others | F4: Insurance | G4: Finance | H4: Hydro | I4: Dev. | J4: Total
B5: Bank | C5: & Processing | H5: Power | I5: Bank | J5: Rs. in millions
A6: 41624 | B6: 420271.95 | C6: 9474.003 | D6: 7564.7574 | E6: 100500 | F6: 23577.661 | G6: 16846.566 | H6: 37296.251 | I6: 25848.615 | J6: 641379.8
A7: 41626 | B7: 444545.07 | C7: 9474.003 | D7: 7736.6837 | E7: 105000 | F7: 24352.629 | G7: 17327.891 | H7: 38609.941 | I7: 26574.864 | J7: 673621.09
A8: 41627 | B8: 442028.79 | C8: 9474.003 | D8: 8016.0639 | E8: 105000 | F8: 24416.985 | G8: 17789.593 | H8: 38352.697 | I8: 26528.94 | J8: 671607.07
A9: 41627 | B9: 442028.79 | C9: 9474.003 | D9: 8016.0639 | E9: 105000 | F9: 24416.985 | G9: 17789.593 | H9: 38352.697 | I9: 28711.938 | J9: 673790.07
A10: 41630 | B10: 431161.66 | C10: 9474.003 | D10: 8166.4994 | E10: 104700 | F10: 23961.232 | G10: 17899.632 | H10: 37794.365 | I10: 28723.592 | J10: 661880.99
A11: 41631 | B11: 411391.93 | C11: 9474.003 | D11: 8145.0087 | E11: 99750 | F11: 23645.581 | G11: 18035.427 | H11: 37313.682 | I11: 28325.882 | J11: 636081.51
A12: 41632 | B12: 416317.34 | C12: 9474.003 | D12: 8145.0087 | E12: 102000 | F12: 23363.086 | G12: 18100.622 | H12: 37408.234 | I12: 28482.912 | J12: 643291.21
A13: 41634 | B13: 423944.32 | C13: 9662.7465 | D13: 8145.0087 | E13: 102000 | F13: 23985.864 | G13: 17983.526 | H13: 37654.386 | I13: 29047.915 | J13: 652423.77
A14: 41637 | B14: 420620.34 | C14: 9662.7465 | D14: 7844.1376 | E14: 100500 | F14: 23735.37 | G14: 17911.028 | H14: 37486.939 | I14: 29003.381 | J14: 646763.94
A15: 41639 | B15: 414686.62 | C15: 9662.7465 | D15: 7586.2482 | E15: 100350 | F15: 23304.096 | G15: 17762.263 | H15: 36348.089 | I15: 28766.286 | J15: 638466.35
A16: 41640 | B16: 405641.54 | C16: 9662.7465 | D16: 7586.2482 | E16: 98250 | F16: 22617.129 | G16: 17688.063 | H16: 34950.938 | I16: 27954.763 | J16: 624351.43
A17: 41641 | B17: 410090.91 | C17: 9662.7465 | D17: 7844.1376 | E17: 100200 | F17: 23118.661 | G17: 17650.072 | H17: 35394.646 | I17: 27608.298 | J17: 631569.47
... A25: 41653 | B25: 419600.06 | C25: 9470.3202 | D25: 7435.8126 | E25: 100500 | F25: 26290.152 | G25: 18387.356 | H25: 35852.088 | I25: 29591.867 | J25: 647127.66

Sheet  Sensitive Index
A2: NEPSE Sensitive-INDEX
A3: Dec-Jan 2014
A4: Date | B4: Com. | C4: Manufact- | D4: Hotel | E4: Others | F4: Insurance | G4: Finance | H4: Hydro | I4: Dev. | J4: Sensitive
B5: Bank | C5: & Pros. | H5: Power | I5: Bank | J5: INDEX
A6: 41624 | B6: 193.35965 | C6: 411.6 | D6: 614.67647 | E6: 172.88315 | F6: 627.04227 | G6: 86.327618 | H6: 448.3299 | I6: 105.30512 | J6: 191.97061
A7: 41626 | B7: 204.52728 | C7: 411.6 | D7: 628.64639 | E7: 180.62419 | F7: 647.65237 | G7: 88.794094 | H7: 464.12148 | I7: 108.2638 | J7: 201.62071
A8: 41627 | B8: 203.36958 | C8: 411.6 | D8: 651.34751 | E8: 180.62419 | F8: 649.36389 | G8: 91.160012 | H8: 461.02921 | I8: 108.07671 | J8: 201.01789
A9: 41628 | B9: 203.36958 | C9: 411.6 | D9: 651.34751 | E9: 180.62419 | F9: 649.36389 | G9: 91.160012 | H9: 461.02921 | I9: 112.01437 | J9: 201.01789
A10: 41630 | B10: 198.36981 | C10: 411.6 | D10: 663.57119 | E10: 180.10812 | F10: 637.24326 | G10: 91.756708 | H10: 454.31762 | I10: 112.04179 | J10: 197.46663
A11: 41631 | B11: 189.27411 | C11: 411.6 | D11: 661.82495 | E11: 171.59298 | F11: 628.84859 | G11: 92.452819 | H11: 448.53944 | I11: 110.80102 | J11: 189.81027
A12: 41632 | B12: 191.5402 | C12: 411.6 | D12: 661.82495 | E12: 175.46349 | F12: 621.3357 | G12: 92.96043 | H12: 449.67603 | I12: 111.24826 | J12: 191.96054
A13: 41634 | B13: 195.04924 | C13: 419.8 | D13: 661.82495 | E13: 175.46349 | F13: 637.89834 | G13: 92.359052 | H13: 452.63497 | I13: 113.45504 | J13: 194.68573
A14: 41637 | B14: 193.50357 | C14: 419.8 | D14: 637.37759 | E14: 172.88315 | F14: 631.23652 | G14: 91.986721 | H14: 450.62212 | I14: 113.2811 | J14: 192.98623
A15: 41639 | B15: 190.7738 | C15: 419.8 | D15: 616.42271 | E15: 172.62511 | F15: 619.76687 | G15: 91.223264 | H15: 436.93227 | I15: 112.70064 | J15: 190.55504
A16: 41640 | B16: 186.61267 | C16: 419.8 | D16: 616.42271 | E16: 169.01263 | F16: 601.49715 | G16: 90.875977 | H16: 420.13743 | I16: 110.05544 | J16: 186.4153
A17: 41641 | B17: 188.90696 | C17: 419.8 | D17: 637.37759 | E17: 172.36708 | F17: 614.83529 | G17: 90.680793 | H17: 425.47114 | I17: 108.69144 | J17: 188.73082
... A25: 41653 | B25: 193.28732 | C25: 411.44 | D25: 604.19903 | E25: 172.88315 | F25: 699.18031 | G25: 94.468736 | H25: 430.96994 | I25: 116.50057 | J25: 193.38005

Sheet Float Index
A2: Float Market Capitalization & INDEX
A3: Dec- Jan 2014
A4: Date | B4: Float M.Ca | C4: Float | D4: Sen. Float M.Ca | E4: Sensitive
B5: Rs. in millions | C5: Index | D5: Rs. in millions | E5: Float Index
A6: 41624 | B6: 155848.17 | C6: 51.6126 | D6: 104083.4 | E6: 45.155418
A7: 41626 | B7: 160666.66 | C7: 53.208352 | D7: 108975.3 | E7: 47.277716
A8: 41627 | B8: 159996.99 | C8: 52.986576 | D8: 108404.73 | E8: 47.030183
A9: 41628 | B9: 159312.99 | C9: 52.986576 | D9: 107720.73 | E9: 47.030182
A10: 41630 | B10: 157447.64 | C10: 52.368278 | D10: 105749.08 | E10: 46.171171
A11: 41631 | B11: 153831.97 | C11: 51.17947 | D11: 102560.69 | E11: 44.801093
A12: 41632 | B12: 154800.14 | C12: 51.501578 | D12: 103172.59 | E12: 45.06839
A13: 41634 | B13: 157171.51 | C13: 52.290526 | D13: 105251.5 | E13: 45.976508
A14: 41639 | B14: 155320.12 | C14: 51.808772 | D14: 104153 | E14: 45.550299
A15: 41640 | B15: 151322 | C15: 50.513349 | D15: 101041.49 | E15: 44.198955
A16: 41641 | B16: 152690.44 | C16: 51.08153 | D16: 101944.39 | E16: 44.740008
A17: 41644 | B17: 151706.25 | C17: 50.752276 | D17: 100881.16 | E17: 44.273392
... A24: 41653 | B24: 157413.35 | C24: 52.661545 | D24: 104215.77 | E24: 45.73684

Sheet Monthly Closing Price
A2: Monhtly Closing Price and Market Capitalization
C3: Nepse | D3: Nepse | E3: Listed | F3: Paid | G3: Total Paid | H3: Today's | I3: Market
B4: Commercial Bank | C4: Code | D4: Code | E4: Shares | F4: UP | G4: Up Value | H4: Closing | I4: Capitalization
D5: No. | F5: Value | H5: Price | I5: 41653
A6: 1 | B6: Nabil Bank Ltd. | C6: NABIL | D6: 102 | E6: 30460518 | F6: 100 | G6: =+E6*F6 -> 3046051800 | H6: 2220 | I6: =SUM(E6*H6) -> 67622349960
A7: 2 | B7: Nepal Investment Bank Ltd. | C7: NIB | D7: 103 | E7: 41448085 | F7: 100 | G7: =+E7*F7 -> 4144808500 | H7: 1010 | I7: =SUM(E7*H7) -> 41862565850
A8: 3 | B8: Standard Chartered Bank Ltd. | C8: SCB | D8: 104 | E8: 20392900 | F8: 100 | G8: =+E8*F8 -> 2039290000 | H8: 1951 | I8: =SUM(E8*H8) -> 39786547900
A9: 4 | B9: Himalayan Bank Ltd. | C9: HBL | D9: 105 | E9: 27600000 | F9: 100 | G9: =+E9*F9 -> 2760000000 | H9: 890 | I9: =SUM(E9*H9) -> 24564000000
A10: 5 | B10: Nepal SBI Bank Limited | C10: SBI | D10: 106 | E10: 26482515 | F10: 100 | G10: =+E10*F10 -> 2648251500 | H10: 1115 | I10: =SUM(E10*H10) -> 29528004225
A11: 6 | B11: Nepal Bangladesh Bank Ltd. | C11: NBB | D11: 107 | E11: 20103890 | F11: 100 | G11: =+E11*F11 -> 2010389000 | H11: 625 | I11: =SUM(E11*H11) -> 12564931250
A12: 7 | B12: Everest Bank Ltd | C12: EBL | D12: 108 | E12: 17612390 | F12: 100 | G12: =+E12*F12 -> 1761239000 | H12: 2210 | I12: =SUM(E12*H12) -> 38923381900
A13: 8 | B13: Bank of Kathmandu | C13: BOK | D13: 109 | E13: 19202122 | F13: 100 | G13: =+E13*F13 -> 1920212200 | H13: 644 | I13: =SUM(E13*H13) -> 12366166568
A14: 9 | B14: NIC Asia Bank Ltd | C14: NICA | D14: 110 | E14: 23115520 | F14: 100 | G14: =+E14*F14 -> 2311552000 | H14: 814 | I14: =SUM(E14*H14) -> 18816033280
A15: 10 | B15: Machhachapuchhre Bank Ltd | C15: MBL | D15: 111 | E15: 24781817 | F15: 100 | G15: =+E15*F15 -> 2478181700 | H15: 480 | I15: =SUM(E15*H15) -> 11895272160
A16: 11 | B16: Laxmi Bank Limited | C16: LBL | D16: 112 | E16: 16941965 | F16: 100 | G16: =+E16*F16 -> 1694196500 | H16: 522 | I16: =SUM(E16*H16) -> 8843705730
A17: 12 | B17: Kumari Bank Ltd | C17: KBL | D17: 113 | E17: 16033128 | F17: 100 | G17: =+E17*F17 -> 1603312800 | H17: 579 | I17: =SUM(E17*H17) -> 9283181112
... A20: 15 | B20: Siddhartha Bank Limited | C20: SBL | D20: 116 | E20: 18135536 | F20: 100 | G20: =+E20*F20 -> 1813553600 | H20: 600 | I20: =SUM(E20*H20) -> 10881321600
A21: 16 | B21: NMB Bank Ltd. | C21: NMB | D21: 117 | E21: 20000000 | F21: 100 | G21: =F21*E21 -> 2000000000 | H21: 420 | I21: =H21*E21 -> 8400000000
A22: 17 | B22: Grand Bank Ltd. | C22: GRAND | D22: 118 | E22: 20000524 | F22: 100 | G22: =F22*E22 -> 2000052400 | H22: 304 | I22: =H22*E22 -> 6080159296
A23: 18 | B23: Global IME Bank Limited | C23: GBIME | D23: 119 | E23: 24181378 | F23: 100 | G23: =F23*E23 -> 2418137800 | H23: 430 | I23: =H23*E23 -> 10397992540
A24: 19 | B24: KIST Bank Limited | C24: KIST | D24: 120 | E24: 20000000 | F24: 100 | G24: =F24*E24 -> 2000000000 | H24: 234 | I24: =H24*E24 -> 4680000000
A25: 20 | B25: Citizens Bank International Ltd. | C25: CZBIL | D25: 121 | E25: 21000000 | F25: 100 | G25: =F25*E25 -> 2100000000 | H25: 453 | I25: =H25*E25 -> 9513000000
A26: 21 | B26: Prime Commercial Bank Limited | C26: PCBL | D26: 123 | E26: 25744458 | F26: 100 | G26: =F26*E26 -> 2574445800 | H26: 508 | I26: =H26*E26 -> 13078184664
A27: 22 | B27: Sunrise Bank Limited | C27: SRBL | D27: 124 | E27: 21125000 | F27: 100 | G27: =F27*E27 -> 2112500000 | H27: 445 | I27: =H27*E27 -> 9400625000
A28: 23 | B28: Agricultural Development Bank Ltd. | C28: ADBL | D28: 125 | E28: 30375000 | F28: 100 | G28: =F28*E28 -> 3037500000 | H28: 501 | I28: =H28*E28 -> 15217875000
A29: 24 | B29: Sanima Bank Ltd. | C29: SANIMA | D29: 126 | E29: 22173636 | F29: 100 | G29: =F29*E29 -> 2217363600 | H29: 524 | I29: =H29*E29 -> 11618985264
A30: 25 | B30: Janata Bank Nepal Ltd | C30: JBNL | D30: 127 | E30: 20600000 | F30: 100 | G30: =F30*E30 -> 2060000000 | H30: 302 | I30: =H30*E30 -> 6221200000
A31: 26 | B31: Nepal Bank Ltd. | C31: NBL | D31: 101 | E31: 40000000 | F31: 100 | G31: =F31*E31 -> 4000000000 | H31: 356 | I31: =H31*E31 -> 14240000000
A32: 27 | B32: Civil Bank Ltd | C32: CBL | D32: 128 | E32: 20000000 | F32: 100 | G32: =F32*E32 -> 2000000000 | H32: 138 | I32: =H32*E32 -> 2760000000
... A34: 29 | B34: Mega Bank Nepal Ltd. | C34: MEGA | D34: 130 | E34: 23300000 | F34: 100 | G34: =F34*E34 -> 2330000000 | H34: 444 | I34: =H34*E34 -> 10345200000
B35: TOTAL | E35: =SUM(E6:E34) -> 661503492 | G35: =SUM(G6:G34) -> 66150349200 | I35: =SUM(I6:I34) -> 463810195279
B36: Manufacturing and Processing
A37: 30 | B37: Bottlers Nepal Ltd.(Balaju) | C37: BNL | D37: 206 | E37: 1948887 | F37: 100 | G37: =+E37*F37 -> 194888700 | H37: 1680 | I37: =SUM(E37*H37) -> 3274130160
A38: 31 | B38: Nepal Lube Oil Ltd. | C38: NLO | D38: 208 | E38: 203936 | F38: 100 | G38: =+E38*F38 -> 20393600 | H38: 242 | I38: =SUM(E38*H38) -> 49352512
A39: 32 | B39: Nepal Vanaspati Ghee Udhyog Ltd | C39: NVG | D39: 209 | E39: 101250 | F39: 100 | G39: =+E39*F39 -> 10125000 | H39: 300 | I39: =SUM(E39*H39) -> 30375000
A40: 33 | B40: Raghupati Jute Mills Ltd. | C40: RJM | D40: 210 | E40: 1806966 | F40: 100 | G40: =+E40*F40 -> 180696600 | H40: 100 | I40: =SUM(E40*H40) -> 180696600
A41: 34 | B41: Butwal Spinning Mills Ltd. | C41: BSM | D41: 211 | E41: 1306693 | F41: 100 | G41: =+E41*F41 -> 130669300 | H41: 18 | I41: =SUM(E41*H41) -> 23520474
A42: 35 | B42: Gorakhakali Rubber Udhyog Ltd. | C42: GRU | D42: 212 | E42: 3833400 | F42: 75 | G42: =+E42*F42 -> 287505000 | H42: 38 | I42: =SUM(E42*H42) -> 145669200
A43: 36 | B43: Jyoti Spinning Mills Ltd (ord.) | C43: JSM | D43: 213 | E43: 1270288 | F43: 100 | G43: =+E43*F43 -> 127028800 | H43: 27 | I43: =SUM(E43*H43) -> 34297776
A44: 37 | B44: Arun Vanaspati Udhyog Ltd. | C44: AVU | D44: 214 | E44: 550343 | F44: 100 | G44: =+E44*F44 -> 55034300 | H44: 58 | I44: =SUM(E44*H44) -> 31919894
A45: 38 | B45: Bottlers Nepal (Terai)Ltd. | C45: BNT | D45: 215 | E45: 1210000 | F45: 100 | G45: =+E45*F45 -> 121000000 | H45: 1750 | I45: =SUM(E45*H45) -> 2117500000
A46: 39 | B46: Harisiddhi Brick and Tile Fac.Ltd. | C46: HBT | D46: 217 | E46: 18650000 | F46: 10 | G46: =+E46*F46 -> 186500000 | H46: 4.2 | I46: =SUM(E46*H46) -> 78330000
A47: 40 | B47: Birat Shoe Ltd.(Ord.) | C47: BSL | D47: 218 | E47: 165000 | F47: 100 | G47: =+E47*F47 -> 16500000 | H47: 28 | I47: =SUM(E47*H47) -> 4620000
A48: 41 | B48: Uniliver Nepal Ltd. | C48: UNL | D48: 219 | E48: 920700 | F48: 100 | G48: =+E48*F48 -> 92070000 | H48: 10286 | I48: =SUM(E48*H48) -> 9470320200
... A51: 44 | B51: Fluer Himalayan Limited | C51: FHL | D51: 225 | E51: 262102 | F51: 75 | G51: =+E51*F51 -> 19657650 | H51: 75 | I51: =SUM(E51*H51) -> 19657650
A52: 45 | B52: Shree Ram Sugar Mills Ltd | C52: SRS | D52: 227 | E52: =2800000+245990 -> 3045990 | F52: 100 | G52: =+E52*F52 -> 304599000 | H52: 100 | I52: =SUM(E52*H52) -> 304599000
A53: 46 | B53: Nepal Bitumin and Barrel Udyog | C53: NBBU | D53: 228 | E53: 210680 | F53: 100 | G53: =+E53*F53 -> 21068000 | H53: 64 | I53: =SUM(E53*H53) -> 13483520
A54: 47 | B54: Himalayan Distillery Ltd. | C54: HDL | D54: 229 | E54: 4130000 | F54: 100 | G54: =+E54*F54 -> 413000000 | H54: 99 | I54: =SUM(E54*H54) -> 408870000
B55: TOTAL | E55: =SUM(E37:E54) -> 43206235 | G55: =SUM(G37:G54) -> 2539735950 | I55: =SUM(I37:I54) -> 16383131986
B56: Hotels
A57: 48 | B57: Yak and Yeti Hotel Ltd.(Ord.) | C57: YHL | D57: 301 | E57: 2209208 | F57: 100 | G57: =+E57*F57 -> 220920800 | H57: 600 | I57: =SUM(E57*H57) -> 1325524800
A58: 49 | B58: Soaltee Hotel Ltd. | C58: SHL | D58: 302 | E58: 30087191 | F58: 10 | G58: =+E58*F58 -> 300871910 | H58: 346 | I58: =SUM(E58*H58) -> 10410168086
A59: 50 | B59: Taragaon Regency Hotel | C59: TRH | D59: 303 | E59: 7449875 | F59: 100 | G59: =+E59*F59 -> 744987500 | H59: 210 | I59: =SUM(E59*H59) -> 1564473750
A60: 51 | B60: Oriental Hotel Ltd. | C60: OHL | D60: 304 | E60: 5000000 | F60: 100 | G60: =+E60*F60 -> 500000000 | H60: 340 | I60: =SUM(E60*H60) -> 1700000000
B61: TOTAL | E61: =SUM(E57:E60) -> 44746274 | G61: =SUM(G57:G60) -> 1766780210 | I61: =SUM(I57:I60) -> 15000166636
B62: Others.
A63: 52 | B63: Nepal Film Dev.Co. Ltd. | C63: NFD | D63: 403 | E63: =446623+44662 -> 491285 | F63: 100 | G63: =+E63*F63 -> 49128500 | H63: 37.5 | I63: =SUM(E63*H63) -> 18423188
A64: 53 | B64: Nepal Doorsanchar Company Limited | C64: NTC | D64: 404 | E64: 150000000 | F64: 100 | G64: =F64*E64 -> 15000000000 | H64: 670 | I64: =H64*E64 -> 100500000000
E65: =SUM(E63:E64) -> 150491285 | G65: =SUM(G63:G64) -> 15049128500 | I65: =SUM(I63:I64) -> 1.0051842e+11
B66: Hydro Power
A67: 54 | B67: National Hydro Power Co. | C67: NHPC | D67: 901 | E67: =6606630+393370+6851862 -> 13851862 | F67: 100 | G67: =+E67*F67 -> 1385186200 | H67: 83 | I67: =SUM(E67*H67) -> 1149704546
A68: 55 | B68: Butwal Power Co. Ltd. | C68: BPCL | D68: 902 | E68: 10152599 | F68: 100 | G68: =+E68*F68 -> 1015259900 | H68: 1320 | I68: =SUM(E68*H68) -> 13401430680
A69: 56 | B69: Chilime Hydro power Co. | C69: CHCL | D69: 903 | E69: 22713600 | F69: 100 | G69: =+E69*F69 -> 2271360000 | H69: 1511 | I69: =SUM(E69*H69) -> 34320249600
A70: 57 | B70: Arun Valley Hydropower Deve. Co.Ltd | C70: AHPC | D70: 904 | E70: 3506426 | F70: 100 | G70: =+E70*F70 -> 350642600 | H70: 580 | I70: =SUM(E70*H70) -> 2033727080
A71: 58 | B71: Sanima Mai Hydropower Ltd. | C71: SHPC | D71: 905 | E71: 10550000 | F71: 100 | G71: =+E71*F71 -> 1055000000 | H71: 0 | I71: =SUM(E71*H71) -> 0
B72: TOTAL | E72: =SUM(E67:E71) -> 60774487 | G72: =SUM(G67:G71) -> 6077448700 | I72: =SUM(I67:I71) -> 50905111906
B73: Tradings.
A74: 59 | B74: Salt Trading Corporation | C74: STC | D74: 501 | E74: 586645 | F74: 100 | G74: =+E74*F74 -> 58664500 | H74: 213 | I74: =SUM(E74*H74) -> 124955385
A75: 60 | B75: Bishal Bazar Co. Ltd. | C75: BBC | D75: 502 | E75: =273000+218400 -> 491400 | F75: 100 | G75: =+E75*F75 -> 49140000 | H75: 1750 | I75: =SUM(E75*H75) -> 859950000
A76: 61 | B76: Nepal Trading Ltd. | C76: NTL | D76: 507 | E76: 50000 | F76: 50 | G76: =+E76*F76 -> 2500000 | H76: 56 | I76: =SUM(E76*H76) -> 2800000
A77: 62 | B77: Nepal Welfare Company Ltd. | C77: NWC | D77: 508 | E77: 41000 | F77: 50 | G77: =+E77*F77 -> 2050000 | H77: 95 | I77: =SUM(E77*H77) -> 3895000
B78: TOTAL | E78: =SUM(E74:E77) -> 1169045 | G78: =SUM(G74:G77) -> 112354500 | I78: =SUM(I74:I77) -> 991600385
B79: Insurance
A80: 63 | B80: Nepal Insurance Co.Ltd. | C80: NICL | D80: 601 | E80: 1232381 | F80: 100 | G80: =+E80*F80 -> 123238100 | H80: 530 | I80: =SUM(E80*H80) -> 653161930
A81: 64 | B81: Rastriya Beema Sansthan | C81: RBS | D81: 602 | E81: =690474+138525 -> 828999 | F81: 100 | G81: =+E81*F81 -> 82899900 | H81: 2360 | I81: =SUM(E81*H81) -> 1956437640
A82: 65 | B82: National LifeInsu. Co.Ltd. | C82: NLICL | D82: 603 | E82: 5099671 | F82: 100 | G82: =+E82*F82 -> 509967100 | H82: 1901 | I82: =SUM(E82*H82) -> 9694474571
A83: 66 | B83: Himalayan Gen.Insu. Co.Ltd. | C83: HGI | D83: 604 | E83: 2500042 | F83: 100 | G83: =+E83*F83 -> 250004200 | H83: 318 | I83: =SUM(E83*H83) -> 795013356
A84: 67 | B84: United Insurance Co.(Nepal)Ltd. | C84: UIC | D84: 605 | E84: 600000 | F84: 100 | G84: =+E84*F84 -> 60000000 | H84: 306 | I84: =SUM(E84*H84) -> 183600000
A85: 68 | B85: Everest Insurance Co. Ltd. | C85: EIC | D85: 606 | E85: =600000+300000+112500 -> 1012500 | F85: 100 | G85: =+E85*F85 -> 101250000 | H85: 211 | I85: =SUM(E85*H85) -> 213637500
A86: 69 | B86: Premier Insurance co. Ltd. | C86: PIC | D86: 607 | E86: 1173000 | F86: 100 | G86: =+E86*F86 -> 117300000 | H86: 246 | I86: =SUM(E86*H86) -> 288558000
A87: 70 | B87: Neco Insurance Co. | C87: NIL | D87: 608 | E87: 1352216 | F87: 100 | G87: =+E87*F87 -> 135221600 | H87: 211 | I87: =SUM(E87*H87) -> 285317576
A88: 71 | B88: Alliance Insurance Co. Ltd. | C88: AIC | D88: 609 | E88: 1623456 | F88: 100 | G88: =+E88*F88 -> 162345600 | H88: 501 | I88: =SUM(E88*H88) -> 813351456
A89: 72 | B89: Sagarmatha Insurance Co.Ltd | C89: SIC | D89: 610 | E89: 2583180 | F89: 100 | G89: =+E89*F89 -> 258318000 | H89: 1282 | I89: =SUM(E89*H89) -> 3311636760
A90: 73 | B90: NB Insurance Co. Ltd. | C90: NBIL | D90: 611 | E90: 1500000 | F90: 100 | G90: =+E90*F90 -> 150000000 | H90: 81 | I90: =SUM(E90*H90) -> 121500000
A91: 74 | B91: Nepal Life Insurance Co. Ltd. | C91: NLIC | D91: 612 | E91: 6375000 | F91: 100 | G91: =+E91*F91 -> 637500000 | H91: 3550 | I91: =SUM(E91*H91) -> 22631250000
A92: 75 | B92: Life Insurance Co. Nepal | C92: LICN | D92: 613 | E92: 5062500 | F92: 100 | G92: =+E92*F92 -> 506250000 | H92: 2630 | I92: =SUM(E92*H92) -> 13314375000
A93: 76 | B93: Prudential Insurance Co. | C93: PICL | D93: 614 | E93: 2500000 | F93: 100 | G93: =+E93*F93 -> 250000000 | H93: 290 | I93: =SUM(E93*H93) -> 725000000
A94: 77 | B94: Lumbini General Insurance | C94: LGIL | D94: 615 | E94: 1549868 | F94: 100 | G94: =+E94*F94 -> 154986800 | H94: 352 | I94: =SUM(E94*H94) -> 545553536
A95: 78 | B95: Shikhar Insurance Co. Ltd. | C95: SICL | D95: 616 | E95: 1750000 | F95: 100 | G95: =+E95*F95 -> 175000000 | H95: 979 | I95: =SUM(E95*H95) -> 1713250000
A96: 79 | B96: Siddhartha Insurance Ltd. | C96: SIL | D96: 617 | E96: 2508000 | F96: 100 | G96: =+E96*F96 -> 250800000 | H96: 418 | I96: =SUM(E96*H96) -> 1048344000
A97: 80 | B97: Asian Life Insurance Co. Ltd. | C97: ALICL | D97: 618 | E97: 4959589 | F97: 100 | G97: =+E97*F97 -> 495958900 | H97: 710 | I97: =SUM(E97*H97) -> 3521308190
... A101: 84 | B101: NLG Insurance Company Ltd. | C101: NLG | D101: 622 | E101: 2250000 | F101: 100 | G101: =+E101*F101 -> 225000000 | H101: 710 | I101: =SUM(E101*H101) -> 1597500000
B102: TOTAL | E102: =SUM(E80:E101) -> 61342095 | G102: =SUM(G80:G101) -> 6134209500 | I102: =SUM(I80:I101) -> 70252013254
B103: Finance
A104: 85 | B104: Nepal Finance and Saving Co.Ltd. | C104: NFS | D104: 701 | E104: 1359599 | F104: 100 | G104: =E104*F104 -> 135959900 | H104: 90 | I104: =SUM(E104*H104) -> 122363910
A105: 86 | B105: NIDC Capital Markets Ltd. | C105: NCM | D105: 702 | E105: 2332289 | F105: 100 | G105: =E105*F105 -> 233228900 | H105: 174 | I105: =SUM(E105*H105) -> 405818286
A106: 87 | B106: Narayani National Finance Co. Ltd. | C106: NNFC | D106: 703 | E106: 6527636 | F106: 100 | G106: =E106*F106 -> 652763600 | H106: 170 | I106: =SUM(E106*H106) -> 1109698120
A107: 88 | B107: Nepal Share Markets Ltd. | C107: NSM | D107: 704 | E107: 4320000 | F107: 100 | G107: =E107*F107 -> 432000000 | H107: 174 | I107: =SUM(E107*H107) -> 751680000
A108: 89 | B108: Kathmandu Finance Limited. | C108: KFL | D108: 706 | E108: 1778618 | F108: 100 | G108: =E108*F108 -> 177861800 | H108: 144 | I108: =SUM(E108*H108) -> 256120992
A109: 90 | B109: Peoples Finance Limited. | C109: PFCL | D109: 707 | E109: 2956800 | F109: 100 | G109: =E109*F109 -> 295680000 | H109: 160 | I109: =SUM(E109*H109) -> 473088000
...

Sheet Top Ten
A1: List of Top Ten Companies
A2: Dec-Jan 2014
A3: On the Basis of Traded Amount
A4: SN | C4: Name of the Companies | D4: Amount Traded
D5: Rs. in million
B6: 1 | C6: Nepal Bangladesh Bank Ltd. | D6: 699.66
B7: 2 | C7: Nepal Bank Limited | D7: 571.36
B8: 3 | C8: Kumari Bank Ltd | D8: 408.41
B9: 4 | C9: NIC Asia Bank Ltd. | D9: 344.66
B10: 5 | C10: Sanima Bank Ltd. | D10: 322.71
B11: 6 | C11: Nepal Credit And Com. Bank | D11: 308.22
B12: 7 | C12: Chilime Hydro power Co. | D12: 271.55
B13: 8 | C13: Agriculture Development Bank | D13: 251.11
B14: 9 | C14: Everest Bank Ltd. | D14: 238.78
B15: 10 | C15: Machhapuchhre Bank Ltd. | D15: 231.52
A37: On the Basis of Number of Shares Traded
A38: SN | C38: Name of the Companies | D38: No Of Share
D39: (Traded in '000)
B40: 1 | C40: Nabil Balance Fund 1 | D40: 1672.61
B41: 2 | C41: Nepal Bank Limited | D41: 1624.74
B42: 3 | C42: Nepal Bangladesh Bank Ltd. | D42: 1099.39
B43: 4 | C43: Kist Bank Ltd. | D43: 888.89
B44: 5 | C44: Kumari Bank Ltd | D44: 779.61
B45: 6 | C45: Nepal Credit And Com. Bank | D45: 732.86
B46: 7 | C46: Siddhartha Inv. Growth Scheme-1 | D46: 730.77
B47: 8 | C47: Sanima Bank Ltd. | D47: 635.05
B48: 9 | C48: Machhapuchhre Bank Ltd. | D48: 539.49
B49: 10 | C49: Agriculture Development Bank | D49: 530.36
A81: On the Basis of Number of Transactions
A82: SN | C82: Name of the Companies | D82: No of Transactions
B84: 1 | C84: Mega Bank Nepal Ltd. | D84: 3063
B85: 2 | C85: Agriculture Development Bank Limited | D85: 2937
B86: 3 | C86: Nepal Bangladesh Bank Ltd. | D86: 2184
B87: 4 | C87: NIC Asia Bank Ltd. | D87: 1742
B88: 5 | C88: Rural Microfinance Dev Centre Ltd. | D88: 1723
B89: 6 | C89: Nepal Bank Limited | D89: 1684
B90: 7 | C90: Kumari Bank Ltd | D90: 1622
B91: 8 | C91: Apex Development Bank Ltd. | D91: 1620
B92: 9 | C92: Sana Kisan Bikas Bank Ltd | D92: 1577
B93: 10 | C93: Nepal Credit And Com. Bank | D93: 1472
A124: On the Basis of Market Capitalization
A125: SN | C125: Name of the Companies | D125: Capitalization
D126: Rs. In Million
B127: 1 | C127: Nepal Doorsanchar Company Limited | D127: 10500
B128: 2 | C128: Nabil Bank Ltd. | D128: 67622.35
B129: 3 | C129: Nepal Investment Bank Ltd. | D129: 41862.57
B130: 4 | C130: Standard Chartered Bank Ltd. | D130: 39786.548
B131: 5 | C131: Everest Bank Ltd | D131: 38923.382
B132: 6 | C132: Chilime Hydro power Co. | D132: 34320.25
B133: 7 | C133: Nepal SBI Bank Limited | D133: 29528.004
B134: 8 | C134: Himalayan Bank Ltd. | D134: 24564
B135: 9 | C135: Nepal Life Insurance Co. Ltd. | D135: 22631.25
B136: 10 | C136: NIC Asia Bank Ltd | D136: 18816.033
